modelzilla/.DS_Store
modelzilla/__init__.py
modelzilla/main.py
modelzilla/media.py
modelzilla/pipeline.py
modelzilla/plugins/__init__.py
modelzilla/plugins/hf_object_det.py
modelzilla/sinks.py
modelzilla-0.1.0.dist-info/LICENSE
modelzilla-0.1.0.dist-info/METADATA
modelzilla-0.1.0.dist-info/WHEEL
modelzilla-0.1.0.dist-info/entry_points.txt
modelzilla-0.1.0.dist-info/RECORD
