Metadata-Version: 2.3
Name: modelzilla
Version: 0.1.0
Summary: It is a lightweight Python package that enables developers to transform any AI model into a fully functional Command-Line Interface (CLI) plugin
Home-page: https://github.com/David-rn/modelzilla/
License: Apache License
Author: David Redo
Author-email: dredonieto@gmail.com
Requires-Python: >=3.10,<3.13
Classifier: License :: OSI Approved :: Apache Software License
Classifier: Programming Language :: Python
Classifier: Programming Language :: Python :: 3
Classifier: Programming Language :: Python :: 3.10
Classifier: Programming Language :: Python :: 3.11
Classifier: Programming Language :: Python :: 3.12
Provides-Extra: hf
Requires-Dist: numpy (<2.0) ; extra == "hf"
Requires-Dist: supervision (>=0.25.1)
Requires-Dist: timm (>=1.0.13) ; extra == "hf"
Requires-Dist: torch (>=2.1.0) ; extra == "hf"
Requires-Dist: transformers (>=4.47.1) ; extra == "hf"
Project-URL: Issues, https://github.com/David-rn/modelzilla/issues
